CHANGES.md
MANIFEST.in
Makefile
README.rst
setup.cfg
setup.py
redis_dashboard/__init__.py
redis_dashboard/common.py
redis_dashboard/models.py
redis_dashboard/tests.py
redis_dashboard/views.py
redis_dashboard.egg-info/PKG-INFO
redis_dashboard.egg-info/SOURCES.txt
redis_dashboard.egg-info/dependency_links.txt
redis_dashboard.egg-info/requires.txt
redis_dashboard.egg-info/top_level.txt